grokadamw/__init__.py
grokadamw/grokadamw.py
grokadamw-0.1.2.dist-info/METADATA
grokadamw-0.1.2.dist-info/WHEEL
grokadamw-0.1.2.dist-info/top_level.txt
grokadamw-0.1.2.dist-info/RECORD
