Metadata-Version: 2.1
Name: grokadamw
Version: 0.1.2
Summary: GrokAdamW optimizer for PyTorch
Author-email: Your Name <your.email@example.com>
Project-URL: Homepage, https://github.com/yourusername/grokadamw
Project-URL: Bug Tracker, https://github.com/yourusername/grokadamw/issues
Keywords: pytorch,optimizer,machine learning
Classifier: Development Status :: 3 - Alpha
Classifier: Intended Audience :: Developers
Classifier: License :: OSI Approved :: MIT License
Classifier: Operating System :: OS Independent
Classifier: Programming Language :: Python :: 3
Classifier: Programming Language :: Python :: 3.7
Classifier: Programming Language :: Python :: 3.8
Classifier: Programming Language :: Python :: 3.9
Classifier: Programming Language :: Python :: 3.10
Requires-Python: >=3.7
Requires-Dist: torch>=1.0.0
